{
  "type": "FeatureCollection",
  "name": "temperatura_pernambuco_2024",
  "features": [
    {
      "type": "Feature",
      "properties": {
        "municipio_id": 2604106,
        "municipio_nome": "Recife",
        "data": "2024-03-23",
        "temperatura_c": 28.5,
        "sensacao_termica_c": 32.1,
        "umidade_percent": 72
      },
      "geometry": {
        "type": "Point",
        "coordinates": [-34.88, -8.05]
      }
    },
    {
      "type": "Feature",
      "properties": {
        "municipio_id": 2611101,
        "municipio_nome": "Caruaru",
        "data": "2024-03-23",
        "temperatura_c": 31.2,
        "sensacao_termica_c": 35.8,
        "umidade_percent": 55
      },
      "geometry": {
        "type": "Point",
        "coordinates": [-35.97, -8.28]
      }
    }
  ]
}
